README.md
setup.py
viz_alchemy/__init__.py
viz_alchemy/__main__.py
viz_alchemy/main.py
viz_alchemy/version.py
viz_alchemy.egg-info/PKG-INFO
viz_alchemy.egg-info/SOURCES.txt
viz_alchemy.egg-info/dependency_links.txt
viz_alchemy.egg-info/entry_points.txt
viz_alchemy.egg-info/requires.txt
viz_alchemy.egg-info/top_level.txt